setup.cfg
setup.py
antlia/__init__.py
antlia/antlia.py
antlia/builder.py
antlia/dialog.py
antlia/message.py
antlia/parser.py
antlia/rect.py
antlia/renderer.py
antlia/user.py
antlia.egg-info/PKG-INFO
antlia.egg-info/SOURCES.txt
antlia.egg-info/dependency_links.txt
antlia.egg-info/requires.txt
antlia.egg-info/top_level.txt
antlia/blueprint/__init__.py
antlia/blueprint/circle.py
antlia/blueprint/picture.py
antlia/blueprint/primitive.py
antlia/blueprint/rectangle.py
antlia/blueprint/text.py
antlia/blueprint/unicode.py
antlia/elements/__init__.py
antlia/elements/button.py
antlia/elements/color.py
antlia/elements/const.py
antlia/elements/element.py
antlia/elements/empty.py
antlia/elements/grid.py
antlia/elements/image.py
antlia/elements/label.py
antlia/elements/progress.py
antlia/elements/table.py
antlia/elements/translate.py
antlia/elements/window.py
antlia/lib/SDL2.dll
antlia/lib/SDL2_image.dll
antlia/lib/SDL2_ttf.dll
antlia/lib/libfreetype-6.dll
antlia/lib/libjpeg-9.dll
antlia/lib/libpng16-16.dll
antlia/lib/libtiff-5.dll
antlia/lib/libwebp-4.dll
antlia/lib/zlib1.dll
antlia/resources/lato-light.ttf
antlia/resources/material-icons.ttf
antlia/resources/roboto-light.ttf